themis/__init__.py
themis/auto.py
themis/cbuild.py
themis/codegen.py
themis/codehelpers.py
themis/drive.py
themis/frc.py
themis/joystick.py
themis/libthemis-frc.so
themis/pwm.py
themis/themis.h
themis/timers.py
themis/util.py
themis/cgen/__init__.py
themis/cgen/counter.py
themis/cgen/optimizer.py
themis/cgen/templates.py
themis/channel/__init__.py
themis/channel/boolean.py
themis/channel/discrete.py
themis/channel/event.py
themis/channel/float.py
themis-0.1.0.dist-info/DESCRIPTION.rst
themis-0.1.0.dist-info/METADATA
themis-0.1.0.dist-info/RECORD
themis-0.1.0.dist-info/WHEEL
themis-0.1.0.dist-info/metadata.json
themis-0.1.0.dist-info/top_level.txt
